ohdsi/database_connector/__init__.py
ohdsi/database_connector/java/postgresql-42.2.18.jar
ohdsi_database_connector-0.4.0.dist-info/METADATA
ohdsi_database_connector-0.4.0.dist-info/WHEEL
ohdsi_database_connector-0.4.0.dist-info/licenses/LICENSE
ohdsi_database_connector-0.4.0.dist-info/RECORD
