Metadata-Version: 2.4
Name: ohdsi-database-connector
Version: 0.4.0
Summary: Python wrapper for the OHDSI R packages
Project-URL: Homepage, https://github.com/vantage6/python-ohdsi
Project-URL: Repository, https://github.com/vantage6/python-ohdsi
Project-URL: Documentation, https://python-ohdsi.readthedocs.io/en/latest/
Project-URL: Bug Tracker, https://github.com/vantage6/python-ohdsi/issues
Author: Vantage6 Team
Maintainer-email: Frank Martin <f.martin@iknl.nl>, Bart van Beusekom <b.vanbeusekom@iknl.nl>
License:                                  Apache License
License-File: LICENSE
Keywords: database-connector,healthcare,ohdsi,omop,r,vantage6
Classifier: Development Status :: 4 - Beta
Classifier: Intended Audience :: Developers
Classifier: Intended Audience :: Science/Research
Classifier: License :: OSI Approved :: Apache Software License
Classifier: Operating System :: OS Independent
Classifier: Programming Language :: Python :: 3
Classifier: Programming Language :: Python :: 3.13
Classifier: Topic :: Scientific/Engineering :: Artificial Intelligence
Classifier: Topic :: Software Development :: Libraries :: Python Modules
Requires-Python: >=3.13
Requires-Dist: rpy2<4.0.0,>=3.5.12
Provides-Extra: dev
